nonebot/adapters/mail/__init__.py
nonebot/adapters/mail/adapter.py
nonebot/adapters/mail/bot.py
nonebot/adapters/mail/config.py
nonebot/adapters/mail/event.py
nonebot/adapters/mail/exception.py
nonebot/adapters/mail/log.py
nonebot/adapters/mail/message.py
nonebot/adapters/mail/model.py
nonebot/adapters/mail/utils.py
nonebot_adapter_mail-1.0.0a7.dist-info/METADATA
nonebot_adapter_mail-1.0.0a7.dist-info/WHEEL
nonebot_adapter_mail-1.0.0a7.dist-info/entry_points.txt
nonebot_adapter_mail-1.0.0a7.dist-info/licenses/LICENCE
nonebot_adapter_mail-1.0.0a7.dist-info/RECORD
