Metadata-Version: 2.1
Name: nonebot-adapter-mail
Version: 1.0.0a7
Summary: Mail adapter for nonebot2
Author-Email: mobyw <mobyw66@gmail.com>
License: MIT
Requires-Python: <4.0,>=3.9
Requires-Dist: nonebot2~=2.3
Requires-Dist: aiosmtplib~=3.0
Requires-Dist: aioimaplib~=1.1
Requires-Dist: pydantic[email]!=2.5.0,!=2.5.1,<3.0.0,>=1.10.0
Requires-Dist: mail-parser~=4.0
